README.rst
functable.py
setup.py
functable.egg-info/PKG-INFO
functable.egg-info/SOURCES.txt
functable.egg-info/dependency_links.txt
functable.egg-info/requires.txt
functable.egg-info/top_level.txt