Metadata-Version: 1.0
Name: functable
Version: 0.2
Summary: A small utility for grouping functions/methods into a table.
Home-page: https://github.org/nejucomo/functable
Author: Nathan Wilcox
Author-email: nejucomo@gmail.com
License: GPLv3
Platform: UNKNOWN
